{
  "ranAt": "2026-04-27T11:04:25.576Z",
  "iter": 20,
  "warmup": 2,
  "results": [
    {
      "name": "health.live",
      "method": "GET",
      "url": "/health/liveness",
      "iter": 20,
      "errors": 0,
      "lastStatus": 200,
      "bytes": 49,
      "min": 0.9884170000000267,
      "p50": 1.5549170000001595,
      "p95": 3.603791000000001,
      "p99": 3.603791000000001,
      "max": 3.603791000000001,
      "avg": 1.7070311499999888
    },
    {
      "name": "health.ready",
      "method": "GET",
      "url": "/health/readiness",
      "iter": 20,
      "errors": 0,
      "lastStatus": 200,
      "bytes": 101,
      "min": 254.37120800000048,
      "p50": 312.5793329999997,
      "p95": 1140.0955000000004,
      "p99": 1140.0955000000004,
      "max": 1140.0955000000004,
      "avg": 412.8511333499999
    },
    {
      "name": "health.root",
      "method": "GET",
      "url": "/health",
      "iter": 20,
      "errors": 0,
      "lastStatus": 200,
      "bytes": 161,
      "min": 253.41525000000183,
      "p50": 303.87962499999776,
      "p95": 888.997041999999,
      "p99": 888.997041999999,
      "max": 888.997041999999,
      "avg": 406.59346270000003
    },
    {
      "name": "auth.me",
      "method": "GET",
      "url": "/auth/me",
      "iter": 20,
      "errors": 0,
      "lastStatus": 200,
      "bytes": 156,
      "min": 520.5366250000006,
      "p50": 728.3313339999986,
      "p95": 1733.2437500000015,
      "p99": 1733.2437500000015,
      "max": 1733.2437500000015,
      "avg": 908.7939916500002
    },
    {
      "name": "categories.list",
      "method": "GET",
      "url": "/categories",
      "iter": 20,
      "errors": 0,
      "lastStatus": 200,
      "bytes": 970,
      "min": 520.2086249999993,
      "p50": 718.6274170000033,
      "p95": 2152.9405000000042,
      "p99": 2152.9405000000042,
      "max": 2152.9405000000042,
      "avg": 888.1991376000005
    },
    {
      "name": "categories.dailyStats",
      "method": "GET",
      "url": "/categories/stats/daily",
      "iter": 20,
      "errors": 0,
      "lastStatus": 200,
      "bytes": 388,
      "min": 1211.931832999995,
      "p50": 1272.5488750000077,
      "p95": 5233.689624999999,
      "p99": 5233.689624999999,
      "max": 5233.689624999999,
      "avg": 1594.2725063000023
    },
    {
      "name": "categories.byId",
      "method": "GET",
      "url": "/categories/CAT-01",
      "iter": 20,
      "errors": 0,
      "lastStatus": 200,
      "bytes": 406,
      "min": 863.2935410000064,
      "p50": 1023.4987499999988,
      "p95": 1348.0867080000025,
      "p99": 1348.0867080000025,
      "max": 1348.0867080000025,
      "avg": 1046.4776519500003
    },
    {
      "name": "products.list.default",
      "method": "GET",
      "url": "/products?page=1&pageSize=20",
      "iter": 20,
      "errors": 0,
      "lastStatus": 200,
      "bytes": 1630,
      "min": 1759.5061249999853,
      "p50": 1976.047292000003,
      "p95": 2312.2490000000107,
      "p99": 2312.2490000000107,
      "max": 2312.2490000000107,
      "avg": 1959.3243333500009
    },
    {
      "name": "products.list.large",
      "method": "GET",
      "url": "/products?page=1&pageSize=200",
      "iter": 20,
      "errors": 0,
      "lastStatus": 200,
      "bytes": 1631,
      "min": 1760.3825829999987,
      "p50": 1910.634457999986,
      "p95": 2140.6881669999857,
      "p99": 2140.6881669999857,
      "max": 2140.6881669999857,
      "avg": 1934.7273812499946
    },
    {
      "name": "products.list.search",
      "method": "GET",
      "url": "/products?q=tomato",
      "iter": 20,
      "errors": 0,
      "lastStatus": 200,
      "bytes": 448,
      "min": 1771.7526659999858,
      "p50": 1945.0699580000073,
      "p95": 2348.078291999991,
      "p99": 2348.078291999991,
      "max": 2348.078291999991,
      "avg": 2001.2552103999988
    },
    {
      "name": "products.list.byCategory",
      "method": "GET",
      "url": "/products?categoryId=CAT-01",
      "iter": 20,
      "errors": 0,
      "lastStatus": 200,
      "bytes": 448,
      "min": 1659.3054169999668,
      "p50": 1933.484999999986,
      "p95": 2563.1953329999815,
      "p99": 2563.1953329999815,
      "max": 2563.1953329999815,
      "avg": 1975.221929199998
    },
    {
      "name": "products.list.activeOnly",
      "method": "GET",
      "url": "/products?status=Active",
      "iter": 20,
      "errors": 0,
      "lastStatus": 200,
      "bytes": 1225,
      "min": 1707.6970830000355,
      "p50": 1918.467667000019,
      "p95": 2425.2876669999678,
      "p99": 2425.2876669999678,
      "max": 2425.2876669999678,
      "avg": 1956.549697799998
    },
    {
      "name": "products.byId",
      "method": "GET",
      "url": "/products/PRD-001",
      "iter": 20,
      "errors": 0,
      "lastStatus": 200,
      "bytes": 404,
      "min": 849.3860839999979,
      "p50": 971.2939999999944,
      "p95": 1403.2966250000172,
      "p99": 1403.2966250000172,
      "max": 1403.2966250000172,
      "avg": 1000.1789520500054
    },
    {
      "name": "products.history",
      "method": "GET",
      "url": "/products/PRD-001/history",
      "iter": 20,
      "errors": 1,
      "lastStatus": 200,
      "bytes": 1809,
      "min": 1427.451166999992,
      "p50": 2069.146375000011,
      "p95": 17764.138208999997,
      "p99": 17764.138208999997,
      "max": 17764.138208999997,
      "avg": 3194.9460374999994
    },
    {
      "name": "stockEntries.list",
      "method": "GET",
      "url": "/stock-entries?page=1&pageSize=20",
      "iter": 20,
      "errors": 0,
      "lastStatus": 200,
      "bytes": 1025,
      "min": 1851.8974589999998,
      "p50": 2105.637541999982,
      "p95": 2783.241291000042,
      "p99": 2783.241291000042,
      "max": 2783.241291000042,
      "avg": 2201.342108400003
    },
    {
      "name": "stockEntries.byProduct",
      "method": "GET",
      "url": "/stock-entries?productId=PRD-001",
      "iter": 20,
      "errors": 0,
      "lastStatus": 200,
      "bytes": 44,
      "min": 1530.1617090000072,
      "p50": 1603.0739579999936,
      "p95": 1990.6445420000236,
      "p99": 1990.6445420000236,
      "max": 1990.6445420000236,
      "avg": 1656.0189375499963
    },
    {
      "name": "stockEntries.byId",
      "method": "GET",
      "url": "/stock-entries/STK-001",
      "iter": 20,
      "errors": 20,
      "lastStatus": 404,
      "bytes": 123,
      "min": 566.9763749999693,
      "p50": 650.4816659999778,
      "p95": 992.5857079999987,
      "p99": 992.5857079999987,
      "max": 992.5857079999987,
      "avg": 665.425164449992
    },
    {
      "name": "stockAdj.list",
      "method": "GET",
      "url": "/stock-adjustments?page=1&pageSize=20",
      "iter": 20,
      "errors": 0,
      "lastStatus": 200,
      "bytes": 3997,
      "min": 1795.4371670000255,
      "p50": 1905.141917000059,
      "p95": 2537.7721669999883,
      "p99": 2537.7721669999883,
      "max": 2537.7721669999883,
      "avg": 1990.055952099996
    }
  ]
}